shoobx/__init__.py
shoobx/mocks3/__init__.py
shoobx/mocks3/config.py
shoobx/mocks3/models.py
shoobx/mocks3/responses.py
shoobx/mocks3/run.py
shoobx/mocks3/urls.py
shoobx/mocks3/wsgi.py
shoobx/mocks3/tests/__init__.py
shoobx/mocks3/tests/test_config.py
shoobx/mocks3/tests/test_s3_boto3.py
shoobx_mocks3-5.1.1.data/data/config/mocks3.cfg
shoobx_mocks3-5.1.1.data/data/config/uwsgi.ini
shoobx_mocks3-5.1.1.dist-info/METADATA
shoobx_mocks3-5.1.1.dist-info/WHEEL
shoobx_mocks3-5.1.1.dist-info/entry_points.txt
shoobx_mocks3-5.1.1.dist-info/top_level.txt
shoobx_mocks3-5.1.1.dist-info/RECORD
