Metadata-Version: 2.4
Name: shoobx.mocks3
Version: 5.1.1
Summary: Shoobx Mock S3 Implementation
Author-email: "Shoobx, Inc." <dev@shoobx.com>
License: Proprietary
Project-URL: Homepage, http://shoobx.com/
Keywords: amazon,aws,s3,mock,moto
Classifier: Development Status :: 5 - Production/Stable
Classifier: Intended Audience :: Developers
Classifier: License :: Other/Proprietary License
Classifier: Programming Language :: Python
Classifier: Programming Language :: Python :: 3
Classifier: Programming Language :: Python :: 3.9
Classifier: Programming Language :: Python :: 3.10
Classifier: Programming Language :: Python :: 3.11
Classifier: Programming Language :: Python :: Implementation :: CPython
Classifier: Programming Language :: Python :: Implementation :: PyPy
Classifier: Natural Language :: English
Classifier: Operating System :: OS Independent
Classifier: Topic :: Internet :: WWW/HTTP
Classifier: Topic :: Office/Business
Requires-Dist: boto3
Requires-Dist: moto[server]>=5.0.0
Requires-Dist: flask_cors
Requires-Dist: pytz
Provides-Extra: test
Requires-Dist: coverage; extra == "test"
Requires-Dist: freezegun; extra == "test"
Requires-Dist: junitxml; extra == "test"
Requires-Dist: mock; extra == "test"
Requires-Dist: python-subunit; extra == "test"
Requires-Dist: pytz; extra == "test"
Requires-Dist: zope.testrunner; extra == "test"
Provides-Extra: dev
Requires-Dist: ipdb; extra == "dev"
Requires-Dist: pdbpp; extra == "dev"
